setup.cfg
setup.py
socket-gatekeeper-connect
socket-gatekeeperd
socket_gatekeeper/GatekeeperSocket.py
socket_gatekeeper/Handler.py
socket_gatekeeper/Listener.py
socket_gatekeeper/MappingsParser.py
socket_gatekeeper/__init__.py
socket_gatekeeper/utils.py
socket_gatekeeper.egg-info/PKG-INFO
socket_gatekeeper.egg-info/SOURCES.txt
socket_gatekeeper.egg-info/dependency_links.txt
socket_gatekeeper.egg-info/requires.txt
socket_gatekeeper.egg-info/top_level.txt