Metadata-Version: 1.1
Name: socket-gatekeeper
Version: 1.3.2
Summary: Add authentication and enhance security to any existing service/protocol
Home-page: https://github.com/kata198/socket-gatekeeper
Author: Tim Savannah
Author-email: kata198@gmail.com
License: LGPLv2
Keywords: socket,password,gatekeeper,security,auth,access,control,add,authenticate,RSA
Platform: UNKNOWN
Classifier: Development Status :: 5 - Production/Stable
Classifier: Programming Language :: Python
Classifier: License :: OSI Approved :: GNU Lesser General Public License v2 (LGPLv2)
Classifier: Programming Language :: Python :: 2
Classifier: Programming Language :: Python :: 2 :: Only
Classifier: Programming Language :: Python :: 2.7
Classifier: Topic :: System :: Networking
Classifier: Topic :: Security
Requires: argumentparser
Requires: pycrypto
